MANIFEST.in
Readme.md
setup.py
webapp2_static.py
webapp2_static.egg-info/PKG-INFO
webapp2_static.egg-info/SOURCES.txt
webapp2_static.egg-info/dependency_links.txt
webapp2_static.egg-info/top_level.txt