Metadata-Version: 1.0
Name: webapp2-static
Version: 0.1
Summary: Simple handler to Serve static files on non Google App Engine (GAE) webapp2 environments
Home-page: http://github.com/robspychala/webapp2_static
Author: Robert Spychala
Author-email: robspychala@gmail.com
License: MIT
Keywords: webapp2
Platform: any
Classifier: Programming Language :: Python :: 2.6
Classifier: Programming Language :: Python :: 2.7
Classifier: Programming Language :: Python :: 3
Classifier: Development Status :: 3 - Alpha
Classifier: Topic :: Database :: Database Engines/Servers
Classifier: Topic :: Software Development :: Libraries :: Python Modules
Classifier: Intended Audience :: Developers
Classifier: License :: OSI Approved :: MIT License
Classifier: Operating System :: OS Independent
